synonym_finder/__init__.py
synonym_finder/synonym_finder.py
synonym_finder-0.0.9.dist-info/METADATA
synonym_finder-0.0.9.dist-info/WHEEL
synonym_finder-0.0.9.dist-info/top_level.txt
synonym_finder-0.0.9.dist-info/zip-safe
synonym_finder-0.0.9.dist-info/RECORD
