Metadata-Version: 2.1
Name: synonym-finder
Version: 0.0.9
Summary: This package consists of synonym finder class 
Home-page: https://github.com/AlouiAmine/Synonym-Finder
Author: Aloui Amine
Author-email: aloui@eurecom.fr
License: MIT
Platform: UNKNOWN
Requires-Python: >=3.5
Requires-Dist: pywikibot
Requires-Dist: SPARQLWrapper
Requires-Dist: nltk
Requires-Dist: sentence-transformers
Requires-Dist: joblib
